djangoexample/__init__.py
djangoexample/manage.py
djangoexample/urls.py
djangoexample/thumbs/__init__.py
djangoexample/thumbs/models.py
djangoexample/thumbs/settings.py
djangoexample/thumbs/tests.py
djangoexample/thumbs/views.py
djangoexample/thumbs/migrations/0001_initial.py
djangoexample/thumbs/migrations/__init__.py
sorethumb/__init__.py
sorethumb/djangothumbnail.py
sorethumb/thumbnail.py
sorethumb/filters/__init__.py
sorethumb/filters/defaultfilters.py
sorethumb/filters/drawfilters.py
sorethumb/templatetags/__init__.py
sorethumb/templatetags/sorethumb.py
sorethumb-1.0.1.dist-info/METADATA
sorethumb-1.0.1.dist-info/RECORD
sorethumb-1.0.1.dist-info/WHEEL
sorethumb-1.0.1.dist-info/top_level.txt
