Metadata-Version: 2.1
Name: sorethumb
Version: 1.0.1
Summary: Thumbnail image processing, with Django integration
Home-page: https://github.com/willmcgugan/sorethumb
Author: Will McGugan
Author-email: will@willmcgugan.com
Maintainer: Will McGugan
Maintainer-email: will@willmcgugan.com
License: UNKNOWN
Platform: UNKNOWN
Classifier: Framework :: Django
Classifier: Intended Audience :: Developers
Classifier: License :: OSI Approved :: BSD License
Classifier: Programming Language :: Python
Classifier: Topic :: Software Development :: Libraries :: Python Modules
Requires-Dist: pillow (>=3.0.0)
